{
  "fitnessActivity": "walking",
  "startTime": "2023-11-17T12:32:42.345Z",
  "endTime": "2023-11-17T12:56:57.285Z",
  "duration": "677.127s",
  "segment": [{
    "fitnessActivity": "walking",
    "startTime": "2023-11-17T12:32:42.345Z",
    "endTime": "2023-11-17T12:33:24.423Z"
  }, {
    "fitnessActivity": "walking",
    "startTime": "2023-11-17T12:33:24.423Z",
    "endTime": "2023-11-17T12:39:59.569Z"
  }, {
    "fitnessActivity": "walking",
    "startTime": "2023-11-17T12:41:04.514Z",
    "endTime": "2023-11-17T12:42:07.138Z"
  }, {
    "fitnessActivity": "walking",
    "startTime": "2023-11-17T12:52:28.928Z",
    "endTime": "2023-11-17T12:54:02.847Z"
  }, {
    "fitnessActivity": "walking",
    "startTime": "2023-11-17T12:55:33.925Z",
    "endTime": "2023-11-17T12:56:34.923Z"
  }, {
    "fitnessActivity": "walking",
    "startTime": "2023-11-17T12:56:34.923Z",
    "endTime": "2023-11-17T12:56:57.285Z"
  }],
  "aggregate": [{
    "metricName": "com.google.heart_minutes.summary",
    "floatValue": 4.0
  }, {
    "metricName": "com.google.calories.expended",
    "floatValue": 62.86802531945381
  }, {
    "metricName": "com.google.step_count.delta",
    "intValue": 1111
  }, {
    "metricName": "com.google.distance.delta",
    "floatValue": 802.9472391125246
  }, {
    "metricName": "com.google.speed.summary",
    "floatValue": 0.7518072199970908
  }, {
    "metricName": "com.google.active_minutes",
    "intValue": 16
  }]
}