{
  "fitnessActivity": "walking",
  "startTime": "2024-05-04T12:15:00Z",
  "endTime": "2024-05-04T12:26:00Z",
  "duration": "660s",
  "segment": [{
    "fitnessActivity": "walking",
    "startTime": "2024-05-04T12:15:00Z",
    "endTime": "2024-05-04T12:26:00Z"
  }],
  "aggregate": [{
    "metricName": "com.google.calories.expended",
    "floatValue": 47.373333333333335
  }, {
    "metricName": "com.google.step_count.delta",
    "intValue": 378
  }, {
    "metricName": "com.google.distance.delta",
    "floatValue": 257.0
  }, {
    "metricName": "com.google.speed.summary",
    "floatValue": 0.3893939393939394
  }, {
    "metricName": "com.google.active_minutes",
    "intValue": 11
  }]
}